wormstools/__init__.py
wormstools/processor.py
wormstools/utils.py
wormstools/worms.py
wormstools/worms_core.py
wormstools-1.3.7.dist-info/LICENSE
wormstools-1.3.7.dist-info/METADATA
wormstools-1.3.7.dist-info/WHEEL
wormstools-1.3.7.dist-info/entry_points.txt
wormstools-1.3.7.dist-info/top_level.txt
wormstools-1.3.7.dist-info/RECORD
