Metadata-Version: 2.1
Name: wormstools
Version: 1.3.7
Summary: Wrapper for WoRMS Rest API
Home-page: https://github.com/Ulises-Rosas/WoRMStools
Author: Ulises Rosas
Author-email: ulisesfrosasp@gmail.com
License: UNKNOWN
Platform: UNKNOWN
Classifier: Programming Language :: Python :: 3
Classifier: License :: OSI Approved :: MIT License
